example/__init__.py
example/seed_entry.py
example/core/__init__.py
example/core/models.py
peewee_seed/__init__.py
peewee_seed-0.1.8.dist-info/METADATA
peewee_seed-0.1.8.dist-info/WHEEL
peewee_seed-0.1.8.dist-info/top_level.txt
peewee_seed-0.1.8.dist-info/RECORD
