Metadata-Version: 2.1
Name: peewee-seed
Version: 0.1.8
Summary: peewee_seed is simple data seeder using peewee.
Home-page: https://github.com/takehaya/peewee_seed
Author: Takeru Hayasaka
Author-email: taketarou2@gmail.com
License: MIT
Platform: any
Classifier: Development Status :: 4 - Beta
Classifier: Topic :: Database
Classifier: Intended Audience :: Developers
Classifier: License :: OSI Approved :: MIT License
Classifier: Operating System :: OS Independent
Classifier: Programming Language :: Python
Requires-Dist: peewee
Requires-Dist: pyyaml
Requires-Dist: flake8
